StudDP-2.0.0.dist-info/DESCRIPTION.rst
StudDP-2.0.0.dist-info/METADATA
StudDP-2.0.0.dist-info/RECORD
StudDP-2.0.0.dist-info/WHEEL
StudDP-2.0.0.dist-info/entry_points.txt
StudDP-2.0.0.dist-info/metadata.json
StudDP-2.0.0.dist-info/top_level.txt
studdp/__init__.py
studdp/config.py
studdp/model.py
studdp/picker.py
studdp/studdp.py
