Metadata-Version: 2.0
Name: StudDP
Version: 2.0.0
Summary: StudIP file downloader in python
Home-page: https://github.com/shoeffner/StudDP.git
Author: Maxim Schuwalow
Author-email: mschuwalow@uos.de
License: MIT
Keywords: StudIP Downloader Osnabrueck UOS utility
Platform: UNKNOWN
Requires-Dist: SecretStorage (>=2.3.1)
Requires-Dist: cffi (>=1.9.1)
Requires-Dist: cryptography (>=1.6)
Requires-Dist: idna (>=2.1)
Requires-Dist: keyring (>=10.1)
Requires-Dist: keyrings.alt
Requires-Dist: memorised
Requires-Dist: pidfile
Requires-Dist: pyasn1 (>=0.1.9)
Requires-Dist: pycparser (>=2.17)
Requires-Dist: python-daemon
Requires-Dist: requests (>=2.12.3)
Requires-Dist: ruamel.yaml
Requires-Dist: six (>=1.10.0)
Requires-Dist: werkzeug
